cv_cli/__init__.py
cv_cli/main.py
cv_cli/utils.py
cv_cli/commands/__init__.py
cv_cli/commands/auth.py
cv_cli/commands/repo.py
cv_cli/commands/vcs.py
notemate_cv-0.2.0.dist-info/METADATA
notemate_cv-0.2.0.dist-info/WHEEL
notemate_cv-0.2.0.dist-info/entry_points.txt
notemate_cv-0.2.0.dist-info/top_level.txt
notemate_cv-0.2.0.dist-info/RECORD
